geom_render/__init__.py
geom_render/core.py
wf_geom_render-0.5.0.dist-info/LICENSE
wf_geom_render-0.5.0.dist-info/WHEEL
wf_geom_render-0.5.0.dist-info/METADATA
wf_geom_render-0.5.0.dist-info/RECORD
