Metadata-Version: 2.1
Name: wf-geom-render
Version: 0.5.0
Summary: A library for projecting 3D geoms into 2D videos
Home-page: https://github.com/WildflowerSchools/wf-geom-render
Keywords: opencv,cv
Author: Theodore Quinn
Author-email: ted.quinn@wildflowerschools.org
Requires-Python: >=3.8,<4.0
Classifier: Intended Audience :: Developers
Classifier: License :: OSI Approved :: MIT License
Classifier: Operating System :: OS Independent
Classifier: Programming Language :: Python
Classifier: Programming Language :: Python :: 3
Classifier: Programming Language :: Python :: 3.8
Classifier: Programming Language :: Python :: 3.9
Classifier: Programming Language :: Python :: 3.10
Classifier: Programming Language :: Python :: 3.11
Requires-Dist: matplotlib (>=3.1.2)
Requires-Dist: numpy (>=1.17)
Requires-Dist: tqdm (>=4.41.1)
Requires-Dist: wf-cv-utils (>=0.3.1)
Project-URL: Repository, https://github.com/WildflowerSchools/wf-geom-render
